google_play_scraper/__init__.py
google_play_scraper/scraper.py
google_play_scraper/util.py
google_play_scraper_dmi-0.9.17.dist-info/LICENSE
google_play_scraper_dmi-0.9.17.dist-info/METADATA
google_play_scraper_dmi-0.9.17.dist-info/WHEEL
google_play_scraper_dmi-0.9.17.dist-info/top_level.txt
google_play_scraper_dmi-0.9.17.dist-info/RECORD
