Metadata-Version: 2.1
Name: google-play-scraper-dmi
Version: 0.9.17
Summary: A lightweight Google Play Store scraper
Home-page: https://github.com/digitalmethodsinitiative/google-play-scraper
Author: Digital Methods Initiative
Author-email: stijn.peeters@uva.nl
Classifier: Programming Language :: Python :: 3
Classifier: License :: OSI Approved :: MIT License
Classifier: Operating System :: OS Independent
Requires-Python: >=3.6
License-File: LICENSE
Requires-Dist: requests
Requires-Dist: beautifulsoup4 (==4.9.3)
